nanonis_xarray/__init__.py
nanonis_xarray/autonesting_dict.py
nanonis_xarray/data.py
nanonis_xarray/header.py
nanonis_xarray/nanonis_dat_backend_entrypoint.py
nanonis_xarray/py.typed
nanonis_xarray/read_dat.py
nanonis_xarray-0.1.8.dist-info/METADATA
nanonis_xarray-0.1.8.dist-info/WHEEL
nanonis_xarray-0.1.8.dist-info/entry_points.txt
nanonis_xarray-0.1.8.dist-info/licenses/LICENSE
nanonis_xarray-0.1.8.dist-info/RECORD
