Metadata-Version: 2.4
Name: nanonis-xarray
Version: 0.1.8
Summary: Read a Nanonis spectroscopy .dat file into a xarray Dataset
Project-URL: Repository, https://github.com/angelo-peronio/nanonis-xarray
Project-URL: Issues, https://github.com/angelo-peronio/nanonis-xarray/issues
Author: Angelo Peronio
License-Expression: MIT
License-File: LICENSE
Keywords: AFM,Atomic Force Microscopy,Inelastic Electron Tunnelling Spectroscopy,Mimea,Nanonis,SPECS,SPS,STM,STM-IETS,STS,Scanning Probe Spectroscopy,Scanning Tunnelling Microscopy,Scanning Tunnelling Spectroscopy,xarray
Classifier: Development Status :: 3 - Alpha
Classifier: Intended Audience :: Science/Research
Classifier: Natural Language :: English
Classifier: Operating System :: OS Independent
Classifier: Programming Language :: Python :: 3
Classifier: Programming Language :: Python :: 3.11
Classifier: Programming Language :: Python :: 3.12
Classifier: Programming Language :: Python :: 3.13
Classifier: Programming Language :: Python :: 3.14
Classifier: Programming Language :: Python :: Implementation :: CPython
Classifier: Topic :: File Formats
Classifier: Topic :: Scientific/Engineering :: Physics
Classifier: Typing :: Typed
Requires-Python: >=3.11
Requires-Dist: numpy>=2.0.0
Requires-Dist: pint-xarray>=0.5
Requires-Dist: xarray>=2024.3.0
